<?xml version="1.0"?>
<!DOCTYPE hibernate-mapping PUBLIC "-//Hibernate/Hibernate Mapping DTD 3.0//EN"
"http://hibernate.sourceforge.net/hibernate-mapping-3.0.dtd">
<!-- Generated 27/06/2013 20:13:01 by Hibernate Tools 3.4.0.CR1 -->
<hibernate-mapping>
    <class name="datos.LineasDeVentas" table="lineasDeVentas" catalog="BD_SSC">
        <composite-id name="id" class="datos.LineasDeVentasId">
            <key-property name="idVenta" type="int">
                <column name="idVenta" />
            </key-property>
            <key-property name="idProducto" type="int">
                <column name="idProducto" />
            </key-property>
        </composite-id>
        <many-to-one name="ventas" class="datos.Ventas" update="false" insert="false" fetch="select">
            <column name="idVenta" not-null="true" />
        </many-to-one>
        <many-to-one name="productos" class="datos.Productos" update="false" insert="false" fetch="select">
            <column name="idProducto" not-null="true" />
        </many-to-one>
        <property name="subtotal" type="java.lang.Float">
            <column name="subtotal" precision="11" scale="0" />
        </property>
        <property name="cantidad" type="java.lang.Integer">
            <column name="cantidad" />
        </property>
    </class>
</hibernate-mapping>
